MANIFEST.in
README.md
setup.cfg
setup.py
transx2gtfs/__init__.py
transx2gtfs/__main__.py
transx2gtfs/agency.py
transx2gtfs/bank_holidays.py
transx2gtfs/calendar.py
transx2gtfs/calendar_dates.py
transx2gtfs/converter.py
transx2gtfs/dataio.py
transx2gtfs/distribute.py
transx2gtfs/routes.py
transx2gtfs/stop_times.py
transx2gtfs/stops.py
transx2gtfs/transxchange.py
transx2gtfs/trips.py
transx2gtfs.egg-info/PKG-INFO
transx2gtfs.egg-info/SOURCES.txt
transx2gtfs.egg-info/dependency_links.txt
transx2gtfs.egg-info/not-zip-safe
transx2gtfs.egg-info/requires.txt
transx2gtfs.egg-info/top_level.txt
transx2gtfs/data/__init__.py
transx2gtfs/data/bank-holidays.json
transx2gtfs/data/test_data/nested.zip
transx2gtfs/data/test_data/packed.zip
transx2gtfs/tests/__init__.py
transx2gtfs/tests/test_calendar.py
transx2gtfs/tests/test_service_journey_pattern.py
transx2gtfs/tests/test_stops.py
transx2gtfs/tests/test_testing.py
transx2gtfs/tests/test_transx2gtfs.py
transx2gtfs/tests/test_xml_reading.py